<default>
	  <prerequisites>
                    <tag type="Skin" />
	  </prerequisites>
          <info>
                    <name>ViXBMC_HD_Slim</name>
                    <packagename>enigma2-plugin-skins-vixbmc_hd_slim</packagename>
                    <shortdescription>vixbmc_hd_slim</shortdescription>
                    <description>vixbmc_hd_slim</description>
          </info>

	  <files type="package"> <!-- without version, without .ipk -->
		<file type="package" name="enigma2-plugin-skins-vixbmc_hd_slim" />
	</files>
</default>
